xssbase/__init__.py
xssbase/cli.py
xssbase/main.py
xssbase/payload.txt
xssbase/utils.py
xssbase/xss.py
xssbase-5.0.1.dist-info/LICENSE
xssbase-5.0.1.dist-info/METADATA
xssbase-5.0.1.dist-info/WHEEL
xssbase-5.0.1.dist-info/entry_points.txt
xssbase-5.0.1.dist-info/top_level.txt
xssbase-5.0.1.dist-info/RECORD
