Metadata-Version: 2.1
Name: xssbase
Version: 5.0.1
Summary: XSSBase: A tool for testing XSS vulnerabilities on websites.
Home-page: https://mrfidal.in/cyber-security/xssbase
Author: MrFidal
Author-email: mrfidal@proton.me
License: MIT
Keywords: xss,cross-site scripting,vulnerability,scanning,security,mrfidal
Classifier: Development Status :: 5 - Production/Stable
Classifier: Intended Audience :: Information Technology
Classifier: Intended Audience :: System Administrators
Classifier: License :: OSI Approved :: MIT License
Classifier: Programming Language :: Python :: 3
Classifier: Programming Language :: Python :: 3.11
Classifier: Topic :: Security
License-File: LICENSE
Requires-Dist: requests
